sentenceLabel/__init__.py
sentenceLabel/sentenceLabel.py
sentenceLabelLib/LeftRightLabel.py
sentenceLabelLib/MainPanel.py
sentenceLabelLib/ScrollPanel.py
sentenceLabelLib/__init__.py
sentenceLabelLib/resources.py
sentenceLabelLib/utils.py
sentenceLabel-1.0.3.dist-info/LICENSE
sentenceLabel-1.0.3.dist-info/METADATA
sentenceLabel-1.0.3.dist-info/WHEEL
sentenceLabel-1.0.3.dist-info/entry_points.txt
sentenceLabel-1.0.3.dist-info/top_level.txt
sentenceLabel-1.0.3.dist-info/RECORD
